zafkiel/__init__.py
zafkiel/_version.py
zafkiel/config.py
zafkiel/decorator.py
zafkiel/exception.py
zafkiel/logger.py
zafkiel/report.py
zafkiel/timer.py
zafkiel/utils.py
zafkiel/device/__init__.py
zafkiel/device/api.py
zafkiel/device/cv.py
zafkiel/device/template.py
zafkiel/device/win.py
zafkiel/ocr/__init__.py
zafkiel/ocr/keyword.py
zafkiel/ocr/models.py
zafkiel/ocr/ocr.py
zafkiel/ocr/utils.py
zafkiel/ui/__init__.py
zafkiel/ui/page.py
zafkiel/ui/switch.py
zafkiel/ui/ui.py
zafkiel-0.3.6.dist-info/licenses/LICENSE
zafkiel-0.3.6.dist-info/METADATA
zafkiel-0.3.6.dist-info/WHEEL
zafkiel-0.3.6.dist-info/top_level.txt
zafkiel-0.3.6.dist-info/RECORD
