Metadata-Version: 2.4
Name: zafkiel
Version: 0.3.6
Summary: A cross-platform UI automation framework based on Airtest and StarRailCopilot.
Author: Aues6uen11Z
License: GPL-3.0 license
Project-URL: Homepage, https://github.com/Aues6uen11Z/Zafkiel
Requires-Python: >=3.6
License-File: LICENSE
Requires-Dist: airtest==1.3.3
Requires-Dist: pyautogui==0.9.54
Requires-Dist: loguru==0.7.2
Requires-Dist: pponnxcr==2.1
Provides-Extra: dev
Requires-Dist: pip-tools; extra == "dev"
Dynamic: license-file
